csv_viz/__init__.py
csv_viz/data_operations.py
csv_viz/main_window.py
csv_viz/utils.py
csv_viz/visualizations.py
csv_viz/plot_settings/__init__.py
csv_viz/plot_settings/boxplot_dialog.py
csv_viz/plot_settings/catplot_dialog.py
csv_viz/plot_settings/error_bars_plot_dialog.py
csv_viz/plot_settings/heatmap_dialog.py
csv_viz/plot_settings/histogram_plot_dialog.py
csv_viz/plot_settings/multiple_data_plot_dialog.py
csv_viz/plot_settings/pairplot_dialog.py
csv_viz/plot_settings/scatter_plot_dialog.py
csv_viz/plot_settings/trendline_plot_dialog.py
csv_viz/plot_settings/violin_plot_dialog.py
csv_visualizer_tool-0.1.0.dist-info/LICENSE
csv_visualizer_tool-0.1.0.dist-info/METADATA
csv_visualizer_tool-0.1.0.dist-info/WHEEL
csv_visualizer_tool-0.1.0.dist-info/entry_points.txt
csv_visualizer_tool-0.1.0.dist-info/top_level.txt
csv_visualizer_tool-0.1.0.dist-info/RECORD
