Metadata-Version: 2.1
Name: csv_visualizer_tool
Version: 0.1.0
Summary: A CSV visualization tool with Seaborn plots and GUI using PyQt5
Home-page: https://github.com/chandrasekarnarayana/CSV_VIZ
Author: Chandrasekar SUBRAMANI NARAYANA
Author-email: chandrasekarnarayana@gmail.com
License-File: LICENSE
Requires-Dist: pandas >=1.3.0
Requires-Dist: matplotlib >=3.4.0
Requires-Dist: seaborn >=0.11.2
Requires-Dist: PyQt5 >=5.12
